certapi/__init__.py
certapi/errors.py
certapi/util.py
certapi/utils.py
certapi/acme/Acme.py
certapi/acme/AcmeError.py
certapi/acme/Challenge.py
certapi/acme/Order.py
certapi/acme/__init__.py
certapi/acme/http.py
certapi/challenge_solver/ChallengeSolver.py
certapi/challenge_solver/FileSystemChallengeSolver.py
certapi/challenge_solver/InmemoryChallengeSolver.py
certapi/challenge_solver/__init__.py
certapi/challenge_solver/dns/__init__.py
certapi/challenge_solver/dns/cloudflare/__init__.py
certapi/challenge_solver/dns/cloudflare/cloudflare_challenge_solver.py
certapi/challenge_solver/dns/cloudflare/cloudflare_client.py
certapi/challenge_solver/dns/digitalocean/__init__.py
certapi/challenge_solver/dns/digitalocean/digitalocean_challenge_solver.py
certapi/challenge_solver/dns/digitalocean/digitalocean_client.py
certapi/client/__init__.py
certapi/client/cert_manager_client.py
certapi/crypto/__init__.py
certapi/crypto/crypto.py
certapi/crypto/crypto_classes.py
certapi/http/HttpClientBase.py
certapi/http/__init__.py
certapi/http/types.py
certapi/issuers/AcmeCertIssuer.py
certapi/issuers/SelfCertIssuer.py
certapi/issuers/__init__.py
certapi/issuers/abstract_certissuer.py
certapi/keystore/FileSystemKeyStore.py
certapi/keystore/KeyStore.py
certapi/keystore/PostgresqlKeyStore.py
certapi/keystore/RemoteKeyStore.py
certapi/keystore/SqliteKeyStore.py
certapi/keystore/__init__.py
certapi/manager/__init__.py
certapi/manager/acme_cert_manager.py
certapi/server/__init__.py
certapi/server/api.py
certapi/server/cert_api.py
certapi/server/key_api.py
certapi-1.0.5.dist-info/METADATA
certapi-1.0.5.dist-info/WHEEL
certapi-1.0.5.dist-info/top_level.txt
certapi-1.0.5.dist-info/RECORD
