Metadata-Version: 2.4
Name: certapi
Version: 1.0.5
Summary: Python Package for managing keys, request SSL certificates from ACME.
Home-page: https://github.com/mesudip/certapi
Author: Sudip Bhattarai
Author-email: sudipbhattarai100@gmail.com
Classifier: Programming Language :: Python :: 3
Classifier: License :: OSI Approved :: MIT License
Classifier: Operating System :: OS Independent
Requires-Python: >=3.6
Requires-Dist: cryptography
Requires-Dist: requests
Dynamic: author
Dynamic: author-email
Dynamic: classifier
Dynamic: description
Dynamic: description-content-type
Dynamic: home-page
Dynamic: requires-dist
Dynamic: requires-python
Dynamic: summary
